{
  "project_info": {
    "project_number": "279354222102",
    "project_id": "go-hadi",
    "storage_bucket": "go-hadi.firebasestorage.app"
  },
  "client": [
    {
      "client_info": {
        "mobilesdk_app_id": "1:279354222102:android:ec5592faed51d2dabcb737",
        "android_client_info": {
          "package_name": "com.arrijal.hadi"
        }
      },
      "oauth_client": [],
      "api_key": [
        {
          "current_key": "AIzaSyBQvx66U9XRlXOIus4_u7HUlRVhQsanG4g"
        }
      ],
      "services": {
        "appinvite_service": {
          "other_platform_oauth_client": []
        }
      }
    }
  ],
  "configuration_version": "1"
}